<?xml version="1.0" encoding="utf-8" ?>
<Defs>

	<AlienRace.RaceSettings>
		<defName>Halfling_Settings</defName>
		<pawnKindSettings>
            <alienslavekinds>
				<li>
					<kindDefs>
						<li>PF2_HalflingSlave</li>
					</kindDefs>
					<chance>20.0</chance>
				</li>
            </alienslavekinds>
            <alienrefugeekinds>
				<li>
					<kindDefs>
						<li>PF2_HalflingRefugee</li>
					</kindDefs>
					<chance>20.0</chance>
				</li>
            </alienrefugeekinds>
			<startingColonists>
				<li>
					<pawnKindEntries>
						<li>
							<kindDefs>
								<li>PF2_HalflingColonist</li>
							</kindDefs>
							<chance>20.0</chance>
						</li>
					</pawnKindEntries>
					<factionDefs>
						<li>PF2_HalflingPlayerColony</li> 
					</factionDefs>
				</li>
				<li>
					<pawnKindEntries>
						<li>
							<kindDefs>
								<li>PF2_HalflingTribal</li>
							</kindDefs>
							<chance>20.0</chance>
						</li>
					</pawnKindEntries>
					<factionDefs>
						<li>PF2_HalflingPlayerTribe</li>
					</factionDefs>
				</li>
			</startingColonists>
            <alienwandererkinds>
                <li>
					<pawnKindEntries>
						<li>
							<kindDefs>
								<li>PF2_HalflingColonist</li>
							</kindDefs>
							<chance>20.0</chance>
						</li>
					</pawnKindEntries>
					<factionDefs>
						<li>PF2_HalflingPlayerColony</li> 
					</factionDefs>
				</li>
				<li>
					<pawnKindEntries>
						<li>
							<kindDefs>
								<li>PF2_HalflingTribal</li>
							</kindDefs>
							<chance>20.0</chance>
						</li>
					</pawnKindEntries>
					<factionDefs>
						<li>PF2_HalflingPlayerTribe</li> 
					</factionDefs>
				</li>
            </alienwandererkinds>
        </pawnKindSettings>
	</AlienRace.RaceSettings>

<AlienRace.ThingDef_AlienRace ParentName="BasePawn">
    <defName>PF2_Halfling</defName>
    <label>halfling</label>
    <description>Optimistic and cheerful, blessed with uncanny luck, and driven by powerful wanderlust, halflings make up for their short stature with an abundance of bravado and curiosity. At once excitable and easygoing, they are the best kind of opportunists, and their passions favor joy over violence. Even in the jaws of danger, halflings rarely lose their sense of humor.</description>
    <alienRace>
        <generalSettings>
			<maleGenderProbability>0.5</maleGenderProbability>
			<immuneToAge>false</immuneToAge>
			<humanRecipeImport>true</humanRecipeImport>
			<immuneToXenophobia>false</immuneToXenophobia>
			<minAgeForAdulthood>20</minAgeForAdulthood>
			<disallowedTraits>
                <li>
                    <defName>Nimble</defName>
				</li>
                <li>
                    <defName>Tough</defName>
				</li>
				<li>
					<defName>Beauty</defName>
					<degree>-2</degree>
				</li>
            </disallowedTraits>
			<alienPartGenerator>
				<alienbodytypes>
					<li>Thin</li>
				</alienbodytypes>
				<customDrawSize>(0.75, 0.75)</customDrawSize>
				<customHeadDrawSize>(0.75, 0.75)</customHeadDrawSize>
				<customPortraitHeadDrawSize>(1.18, 1.18)</customPortraitHeadDrawSize>
				<headOffset>(0.0, -0.08)</headOffset>
			</alienPartGenerator>
        </generalSettings>
        <compatibility>
			<isFlesh>True</isFlesh>
			<isSentient>True</isSentient>
			<hasBlood>True</hasBlood>
        </compatibility>
    </alienRace>	
	<statBases>
		<Mass>35</Mass>
		<MarketValue>1750</MarketValue>
		<MoveSpeed>4.0</MoveSpeed>
		<ComfyTemperatureMin>16</ComfyTemperatureMin>
		<ComfyTemperatureMax>26</ComfyTemperatureMax>
		<LeatherAmount>35</LeatherAmount>
		<RoyalFavorValue>3</RoyalFavorValue>
		<MeleeDodgeChance>15</MeleeDodgeChance>
		<PawnTrapSpringChance>0.1</PawnTrapSpringChance>
		<ForagedNutritionPerDay>0.6</ForagedNutritionPerDay>
		<PlantWorkSpeed>1.2</PlantWorkSpeed>
		<PlantHarvestYield>1.2</PlantHarvestYield>
		<PruningSpeed MayRequire="Ludeon.RimWorld.Ideology">1.2</PruningSpeed>
	</statBases>
	<tools>
		<li>
			<label>left fist</label>
			<capacities>
				<li>Blunt</li>
			</capacities>
			<power>7.4</power>
			<cooldownTime>2</cooldownTime>
			<linkedBodyPartsGroup>LeftHand</linkedBodyPartsGroup>
			<surpriseAttack>
				<extraMeleeDamages>
					<li>
						<def>Stun</def>
						<amount>14</amount>
					</li>
				</extraMeleeDamages>
			</surpriseAttack>
		</li>
		<li>
			<label>right fist</label>
			<capacities>
				<li>Blunt</li>
			</capacities>
			<power>7.4</power>
			<cooldownTime>2</cooldownTime>
			<linkedBodyPartsGroup>RightHand</linkedBodyPartsGroup>
			<surpriseAttack>
				<extraMeleeDamages>
					<li>
						<def>Stun</def>
						<amount>14</amount>
					</li>
				</extraMeleeDamages>
			</surpriseAttack>
		</li>
		<li>
			<label>teeth</label>
			<capacities>
				<li>Bite</li>
			</capacities>
			<power>7.4</power>
			<cooldownTime>2</cooldownTime>
			<linkedBodyPartsGroup>Teeth</linkedBodyPartsGroup>
			<chanceFactor>0.07</chanceFactor>
		</li>
		<li>
			<label>head</label>
			<capacities>
				<li>Blunt</li>
			</capacities>
			<power>4.2</power>
			<cooldownTime>2</cooldownTime>
			<linkedBodyPartsGroup>HeadAttackTool</linkedBodyPartsGroup>
			<ensureLinkedBodyPartsGroupAlwaysUsable>true</ensureLinkedBodyPartsGroupAlwaysUsable>
			<chanceFactor>0.2</chanceFactor>
		</li>
	</tools>
	<race>
		<thinkTreeMain>Humanlike</thinkTreeMain>
		<thinkTreeConstant>HumanlikeConstant</thinkTreeConstant>
		<intelligence>Humanlike</intelligence>
		<makesFootprints>true</makesFootprints>
		<lifeExpectancy>150</lifeExpectancy>
		<leatherDef>Leather_Human</leatherDef>
		<nameGenerator>PF2_NamerPersonHalflingMale</nameGenerator>
		<nameGeneratorFemale>PF2_NamerPersonHalflingFemale</nameGeneratorFemale>
		<useMeatFrom>Human</useMeatFrom>
		<body>Human</body>
		<baseBodySize>0.70</baseBodySize>
		<baseHealthScale>0.9</baseHealthScale>
		<foodType>OmnivoreHuman</foodType>
		<gestationPeriodDays>30</gestationPeriodDays>
		<meatMarketValue>0.8</meatMarketValue>
		<manhunterOnDamageChance>0.20</manhunterOnDamageChance>
		<manhunterOnTameFailChance>0.02</manhunterOnTameFailChance>
		<litterSizeCurve>
			<points>
				<li>(0.5, 0)</li>
				<li>(1, 1)</li>
				<li>(1.01, 0.02)</li>
				<li>(3.5, 0)</li>
			</points>
		</litterSizeCurve>
		<lifeStageAges Inherit="False">
			<li>
				<def>HumanlikeBaby</def>
				<minAge>0</minAge>
			</li>
			<li>
				<def>HumanlikeToddler</def>
				<minAge>2.5</minAge>
			</li>
			<li>
				<def>HumanlikeChild</def>
				<minAge>5</minAge>
			</li>
			<li>
				<def>HumanlikeTeenager</def>
				<minAge>10</minAge>
			</li>
			<li>
				<def>HumanlikeAdult</def>
				<minAge>20</minAge>
			</li>
		</lifeStageAges>
		<soundMeleeHitPawn>Pawn_Melee_Punch_HitPawn</soundMeleeHitPawn>
		<soundMeleeHitBuilding>Pawn_Melee_Punch_HitBuilding</soundMeleeHitBuilding>
		<soundMeleeMiss>Pawn_Melee_Punch_Miss</soundMeleeMiss>
		<soundMeleeDodge>Pawn_MeleeDodge</soundMeleeDodge>
		<specialShadowData>
			<volume>(0.3, 0.8, 0.4)</volume>
			<offset>(0,0,-0.3)</offset>
		</specialShadowData>
		<ageGenerationCurve>
			<points>
				<li>(15,0)</li>
				<li>(20,100)</li>
				<li>(40,100)</li>
				<li>(60,30)</li>
				<li>(80,18)</li>
				<li>(120,10)</li>
				<li>(150,3)</li>
				<li>(170,0)</li>
			</points>
		</ageGenerationCurve>
		<hediffGiverSets>
			<li>OrganicStandard</li>
			<li>Human</li>
		</hediffGiverSets>
		</race>
		<recipes>
			<li>ExciseCarcinoma</li>
			<li>AdministerMechSerumHealer</li>
			<li>RemoveBodyPart</li>
			<li>Euthanize</li>
			<li>Anesthetize</li>
			<li>CureScaria</li>
			<li MayRequire="Ludeon.RimWorld.Royalty">CureBloodRot</li>
			<li MayRequire="Ludeon.RimWorld.Royalty">CureAbasia</li>
		</recipes>
</AlienRace.ThingDef_AlienRace>

</Defs>